npzigloc/LICENSE
npzigloc/README.MD
npzigloc/__init__.py
npzigloc/create_zig_functions.py
npzigloc/npzigwhere.pyx
npzigloc/npzigwhere_compile.py
npzigloc/requirements.txt
npzigloc/thirdparty.json
npzigloc/zignpwhere.zig
npzigloc-0.11.dist-info/LICENSE.rst
npzigloc-0.11.dist-info/METADATA
npzigloc-0.11.dist-info/WHEEL
npzigloc-0.11.dist-info/top_level.txt
npzigloc-0.11.dist-info/RECORD
