Metadata-Version: 2.1
Name: npzigloc
Version: 0.11
Summary: Zig for Numpy
Home-page: https://github.com/hansalemaos/npzigloc
Author: Johannes Fischer
Author-email: aulasparticularesdealemaosp@gmail.com
License: MIT
Keywords: Zig,Numpy
Classifier: Development Status :: 4 - Beta
Classifier: Programming Language :: Python :: 3 :: Only
Classifier: Programming Language :: Python :: 3.10
Classifier: Topic :: Software Development :: Libraries :: Python Modules
Classifier: Topic :: Utilities
License-File: LICENSE.rst
Requires-Dist: Cython
Requires-Dist: numpy
Requires-Dist: setuptools
Requires-Dist: ziglang
